{
  "version": 3,
  "configurePresets": [
    {
      "name": "Default",
      "binaryDir": "${sourceDir}/build",
      "installDir": "${sourceDir}/dist",
      "cacheVariables": {
        "CMAKE_BUILD_TYPE": "Release",
        "CMAKE_MSVC_RUNTIME_LIBRARY": "MultiThreaded"
      }
    },
    {
      "name": "CPU",
      "inherits": [
        "Default"
      ]
    },
    {
      "name": "SYCL",
      "inherits": [
        "Default"
      ],
      "cacheVariables": {
        "GGML_SYCL": "ON",
        "GGML_SYCL_DNN": "ON",
        "GGML_SYCL_F16": "ON",
        "GGML_BACKEND_DL": "ON",
        "BUILD_SHARED_LIBS": "ON"
      }
    },
    {
      "name": "SYCL_INTEL",
      "inherits": [
        "SYCL"
      ],
      "cacheVariables": {
        "GGML_SYCL_TARGET": "INTEL",
        "CMAKE_C_COMPILER": "icx",
        "CMAKE_CXX_COMPILER": "icpx"
      }
    }
  ],
  "buildPresets": [
    {
      "name": "Default",
      "configurePreset": "Default",
      "configuration": "Release"
    },
    {
      "name": "CPU",
      "configurePreset": "Default"
    },
    {
      "name": "SYCL_INTEL",
      "targets": [
        "ggml-sycl"
      ],
      "configurePreset": "SYCL_INTEL"
    }
  ]
}